vectograph/__init__.py
vectograph/helper_classes.py
vectograph/helper_funcs.py
vectograph/kge_models.py
vectograph/transformers.py
vectograph/utils.py
vectograph-0.0.2.dist-info/LICENSE
vectograph-0.0.2.dist-info/METADATA
vectograph-0.0.2.dist-info/WHEEL
vectograph-0.0.2.dist-info/top_level.txt
vectograph-0.0.2.dist-info/RECORD
