Metadata-Version: 2.1
Name: vectograph
Version: 0.0.2
Summary: A set of python modules for applying knowledge graph embedding on tabular data
Home-page: UNKNOWN
Author: Caglar Demir
Author-email: caglardemir8@gmail.com
License: UNKNOWN
Platform: UNKNOWN
Classifier: Programming Language :: Python :: 3
Classifier: License :: OSI Approved :: MIT License
Requires-Python: >=3.6
Requires-Dist: scikit-learn (==0.22.1)
Requires-Dist: pandas (>=1.0.3)
Requires-Dist: rdflib (>=5.0.0)
Requires-Dist: matplotlib (>=3.2.1)
Requires-Dist: torch
Requires-Dist: umap-learn
